rexmex/__init__.py
rexmex/dataset.py
rexmex/metricset.py
rexmex/scorecard.py
rexmex/utils.py
rexmex/metrics/__init__.py
rexmex/metrics/classification.py
rexmex/metrics/coverage.py
rexmex/metrics/ranking.py
rexmex/metrics/rating.py
rexmex-0.1.1.dist-info/LICENSE
rexmex-0.1.1.dist-info/METADATA
rexmex-0.1.1.dist-info/WHEEL
rexmex-0.1.1.dist-info/top_level.txt
rexmex-0.1.1.dist-info/RECORD
