Metadata-Version: 2.1
Name: rexmex
Version: 0.1.1
Summary: A General Purpose Recommender Metrics Library for Fair Evaluation.
Home-page: https://github.com/AstraZeneca/rexmex
Download-URL: https://github.com/AstraZeneca/rexmex/archive/v_00101.tar.gz
Author: Benedek Rozemberczki, Sebastian Nilsson, Piotr Grabowski, Charles Tapley Hoyt, Gavin Edwards
Author-email: bikg@astrazeneca.com
License: Apache License, Version 2.0
Keywords: recommender,nmf,matrix factorisation,system,evaluation metric,ranking,recsys,metric,ranking metric,performance metric
Classifier: Development Status :: 3 - Alpha
Classifier: Intended Audience :: Developers
Classifier: Topic :: Software Development :: Build Tools
Classifier: License :: OSI Approved :: Apache Software License
Classifier: Programming Language :: Python :: 3.7
License-File: LICENSE
Requires-Dist: numpy
Requires-Dist: sklearn
Requires-Dist: pandas (<=1.3.5)
Requires-Dist: scipy
Requires-Dist: scikit-learn
Provides-Extra: test
Requires-Dist: pytest ; extra == 'test'
Requires-Dist: pytest-cov ; extra == 'test'
